statscend/__init__.py
statscend/bn_logistic_regression.py
statscend/datasets.py
statscend/linear_regression.py
statscend/mahalanobis_distance.py
statscend/manova.py
statscend/mn_logistic_regression.py
statscend/ordinal_regression.py
statscend/vif.py
statscend-0.2.2.dist-info/METADATA
statscend-0.2.2.dist-info/WHEEL
statscend-0.2.2.dist-info/licenses/LICENSE
statscend-0.2.2.dist-info/RECORD
