Metadata-Version: 2.1
Name: statscend
Version: 0.2.2
Summary: A Python package for performing various statistical analyses
Project-URL: Homepage, https://github.com/hashimputhiyakath/statscend
Project-URL: Bug Tracker, https://github.com/hashimputhiyakath/statscend/issues
Author-email: Hashim Puthiyakath <hashputhiyakath@gmail.com>
License: MIT License
License-File: LICENSE
Classifier: License :: OSI Approved :: MIT License
Classifier: Operating System :: OS Independent
Classifier: Programming Language :: Python :: 3
Requires-Python: >=3.7
Requires-Dist: numpy
Requires-Dist: pandas
Requires-Dist: seaborn
Requires-Dist: sklearn
Requires-Dist: statsmodels
